shellrosetta/__init__.py
shellrosetta/api.py
shellrosetta/cli.py
shellrosetta/config.py
shellrosetta/core.py
shellrosetta/logging_config.py
shellrosetta/mappings.py
shellrosetta/ml_engine.py
shellrosetta/parser.py
shellrosetta/performance.py
shellrosetta/plugins.py
shellrosetta/security.py
shellrosetta/utils.py
shellrosetta-1.2.1.dist-info/licenses/LICENSE
shellrosetta-1.2.1.dist-info/METADATA
shellrosetta-1.2.1.dist-info/WHEEL
shellrosetta-1.2.1.dist-info/entry_points.txt
shellrosetta-1.2.1.dist-info/top_level.txt
shellrosetta-1.2.1.dist-info/RECORD
